ihip
