Metadata-Version: 1.0
Name: ihip
Version: 1.0.9
Summary: Jupyter integration Package for generating models
Home-page: https://infygithub.ad.infosys.com/veena-devipalamuri/JupyterIntegration.git
Author: Infosys
Author-email: veena.devipalamuri@infosys.com
License: MIT
Platform: UNKNOWN
